Workbook

Sheet README
A1: CopyMe (CpM) — Sprint Tracker
A3: Companion to: COPYME_SPRINT_PLAN.md
A4: Owners: Paul Pereira (US) · Jože Kralj (SI)
A5: Plan date: 2026-05-09
A7: How to use this tracker
A8: • Each row in the 'Sprints' tab is a 1-hour Claude Code unit of work.
A9: • Set Status to: todo → in_progress → done (or blocked).
A10: • 'Owner' is who is executing the sprint right now.
A11: • 'Acceptance' is the canonical pass/fail; mirrors the AC in the markdown plan.
A12: • Filter by Phase or Workstream to plan a working session.
A13: • 'Dashboard' tab auto-counts progress.
A15: Phases
... A34: • Target gates: G0 by 2026-05-12 · G1 by 2026-05-22 · G2 by 2026-06-02 · G3 by 2026-06-09.

Sheet Sprints
A1: ID | B1: Phase | C1: Workstream | D1: Sprint title | E1: Goal / Acceptance | F1: Depends on | G1: Owner | H1: Status | I1: Estimate (hr) | J1: Sprint # | K1: Started | L1: Completed | M1: Notes
A2: S-001 | B2: Sprint 0 | C2: PROD | D2: Hero — remove 'Copies', keep 'Communication That Matters' (corrected per Feedback 3) | E2: H1 reads 'Communication That Matters'; 'Copies' string gone; OG regenerated. Feedback 3 clarified Communication That Matters was never meant to be removed. | F2: — | H2: todo | I2: 1 | M2: Corrected per Feedback 3 (2026-05-10)
A3: S-002 | B3: Sprint 0 | C3: PROD | D3: Hero subhead Rule of 7 rewrite | E3: Replace subhead per Joze's exact wording; remove old strings. | F3: S-001 | H3: todo | I3: 1
A4: S-003 | B4: Sprint 0 | C4: TRUST | D4: Move Rule-of-7 mechanics to Terms | E4: Strip 70/7/last-7 numbers from landing; ensure they live in Terms §3. | F4: S-002 | H4: todo | I4: 1
A5: S-004 | B5: Sprint 0 | C5: TRUST | D5: Fix Terms suspension wording + typo | E5: Reword 'We can suspend' line; fix 'suspened' typo. | F5: — | H5: todo | I5: 1
A6: S-005 | B6: Sprint 0 | C6: PROD | D6: Logo: drop 'Rule of 7' subscript | E6: Clean SVG mark; regenerate favicons; keep legacy lockup in press kit. | F6: — | H6: todo | I6: 1
A7: S-006 | B7: Sprint 0 | C7: PROD | D7: Logo variant: globe-with-figure | E7: Two SVG explorations adding small globe + figure (per original paper). | F7: S-005 | H7: todo | I7: 1
A8: S-007 | B8: Sprint 0 | C8: ENG | D8: Add country code +386 (Slovenia) to phone auth | E8: Slovenia selectable, validated, sample SMS sent in dev. | F8: — | H8: todo | I8: 1
A9: S-008 | B9: Sprint 0 | C9: PROD | D9: Cross-device live test (US ↔ SI) | E9: Install PWA on Paul + Joze phones; exchange messages; capture screenshots. | F9: S-007; S-001..S-005 deployed | H9: todo | I9: 1
A10: S-101 | B10: Phase 1 | C10: ENG | D10: Phone-first sign-up flow | E10: Country code → SMS OTP → display name. | F10: S-007 | H10: todo | I10: 1
A11: S-102 | B11: Phase 1 | C11: ENG | D11: Country picker: full ITU list | E11: 240+ entries; SI/US pinned for context; keyboard-navigable. | F11: S-007 | H11: todo | I11: 1
A12: S-103 | B12: Phase 1 | C12: ENG | D12: OTP backend (provider-agnostic) | E12: Twilio + fallback behind sendOtp() interface. | F12: S-101 | H12: todo | I12: 1
A13: S-104 | B13: Phase 1 | C13: PROD | D13: Onboarding 'first 7 contacts' import | E13: Up to 7; skip allowed; analytics event. | F13: S-101 | H13: todo | I13: 1
A14: S-105 | B14: Phase 1 | C14: PROD | D14: Display-name + avatar setup | E14: Required name, optional avatar, default generator. | F14: S-101 | H14: todo | I14: 1
... A156: B-012 | B156: Business | C156: BIZ | D156: Close the round | E156: Sign + wire; cap-table updated; embargoed announcement. | F156: B-009 or B-010 | H156: todo | I156: 1
A157: S-009 | B157: Sprint 0 | C157: TRUST | D157: Contact email migration to info@copyme1.com | E157: Replace interactiveintel@gmail.com everywhere; DNS+SPF+DKIM+DMARC; old gmail kept as 90-day alias. | F157: — | H157: todo | I157: 1 | M157: NEW per Feedback 3 (2026-05-10) — confirm copyme1.com is registered first
A158: S-010 | B158: Sprint 0 | C158: PROD | D158: Hero: add 'Your World's chart of Communication' as H2 | E158: Below H1 'Communication That Matters' insert H2; OG regenerated. | F158: S-001 | H158: todo | I158: 1 | M158: NEW per Feedback 3 (2026-05-10)
A159: B-013 | B159: Business | C159: BIZ | D159: Use of proceeds — €1M breakdown | E159: Per-line use of funds by category and quarter, summing exactly to €1M; tied to milestones. | F159: B-006 | H159: todo | I159: 1 | M159: NEW per Feedback 3 — Joze asked 'Show use of proceeds'
A160: B-014 | B160: Business | C160: BIZ | D160: Additional investor target list (≥21 names) | E160: 7 SI/EU + 7 US + 7 strategic/corporate; rationale + intro path; ranked. | F160: B-008 | H160: todo | I160: 1 | M160: NEW per Feedback 3 — Joze asked 'Search for other potential targets'
A161: B-015 | B161: Business | C161: BIZ | D161: Timeline-to-launch communique for Joze | E161: 1-page public-shareable timeline with G0..G3 gates; md + pdf. | F161: — | H161: todo | I161: 1 | M161: NEW per Feedback 3 — Joze asked for time estimation
A162: B-016 | B162: Business | C162: TRUST | D162: Definition of 'Customer-ready' gate | E162: Written definition (Functional/Trust/Ops/Regional bars + sign-off matrix). | F162: — | H162: todo | I162: 1 | M162: NEW per Feedback 3 — Joze asked 'Where is the point where clients can apply'

Sheet Dashboard
A1: CopyMe Sprint Dashboard
A3: Overall progress | D3: By Phase | I3: By Workstream
A4: Total sprints | B4: =COUNTA(Sprints!A2:A162) -> 161 | D4: Phase | E4: Total | F4: Done | G4: % complete | I4: Workstream | J4: Total | K4: Done | L4: % complete
A5: Done | B5: =COUNTIF(Sprints!H2:H162,"done") -> 0 | D5: Sprint 0 | E5: =COUNTIF(Sprints!B2:B162,"Sprint 0") -> 10 | F5: =COUNTIFS(Sprints!B2:B162,"Sprint 0",Sprints!H2:H162,"done") -> 0 | G5: =IFERROR(F5/E5,0) -> 0 | I5: ENG | J5: =COUNTIF(Sprints!C2:C162,"ENG") -> 62 | K5: =COUNTIFS(Sprints!C2:C162,"ENG",Sprints!H2:H162,"done") -> 0 | L5: =IFERROR(K5/J5,0) -> 0
A6: In progress | B6: =COUNTIF(Sprints!H2:H162,"in_progress") -> 0 | D6: Phase 1 | E6: =COUNTIF(Sprints!B2:B162,"Phase 1") -> 72 | F6: =COUNTIFS(Sprints!B2:B162,"Phase 1",Sprints!H2:H162,"done") -> 0 | G6: =IFERROR(F6/E6,0) -> 0 | I6: PROD | J6: =COUNTIF(Sprints!C2:C162,"PROD") -> 44 | K6: =COUNTIFS(Sprints!C2:C162,"PROD",Sprints!H2:H162,"done") -> 0 | L6: =IFERROR(K6/J6,0) -> 0
A7: Blocked | B7: =COUNTIF(Sprints!H2:H162,"blocked") -> 0 | D7: Phase 2 | E7: =COUNTIF(Sprints!B2:B162,"Phase 2") -> 37 | F7: =COUNTIFS(Sprints!B2:B162,"Phase 2",Sprints!H2:H162,"done") -> 0 | G7: =IFERROR(F7/E7,0) -> 0 | I7: TRUST | J7: =COUNTIF(Sprints!C2:C162,"TRUST") -> 34 | K7: =COUNTIFS(Sprints!C2:C162,"TRUST",Sprints!H2:H162,"done") -> 0 | L7: =IFERROR(K7/J7,0) -> 0
A8: To do | B8: =COUNTIF(Sprints!H2:H162,"todo") -> 161 | D8: Phase 3 | E8: =COUNTIF(Sprints!B2:B162,"Phase 3") -> 26 | F8: =COUNTIFS(Sprints!B2:B162,"Phase 3",Sprints!H2:H162,"done") -> 0 | G8: =IFERROR(F8/E8,0) -> 0 | I8: BIZ | J8: =COUNTIF(Sprints!C2:C162,"BIZ") -> 21 | K8: =COUNTIFS(Sprints!C2:C162,"BIZ",Sprints!H2:H162,"done") -> 0 | L8: =IFERROR(K8/J8,0) -> 0
A9: % complete | B9: =COUNTIF(Sprints!H2:H162,"done")/COUNTA(Sprints!A2:A162) -> 0 | D9: Business | E9: =COUNTIF(Sprints!B2:B162,"Business") -> 16 | F9: =COUNTIFS(Sprints!B2:B162,"Business",Sprints!H2:H162,"done") -> 0 | G9: =IFERROR(F9/E9,0) -> 0
A10: Hours remaining (est) | B10: =SUMIFS(Sprints!I2:I162,Sprints!H2:H162,"todo")+SUMIFS(Sprints!I2:I162,Sprints!H2:H162,"in_progress") -> 161

Sheet Joze Feedback
A1: # | B1: Date received | C1: From | D1: Topic | E1: Joze's request (verbatim or paraphrase) | F1: Closed by sprint(s) | G1: Status
A2: 1 | B2: 2026-05-07 | C2: Jože | D2: Hero copy | E2: First contact when opening CopyMe page is too dense. Rule of 7 should be felt, not enumerated. Move details to T&C. | F2: S-001, S-002, S-003 | G2: todo
A3: 2 | B3: 2026-05-07 | C3: Jože | D3: Hero copy | E3: New main headline: 'Your World's chart of Communication'. | F3: S-001 | G3: todo
A4: 3 | B4: 2026-05-07 | C4: Jože | D4: Hero copy | E4: Subhead: 'Rule of 7 — A revolutionary constraint system that replaces noise with meaning. Less is more, giving meaning to messages. Infinite impact.' | F4: S-002 | G4: todo
A5: 4 | B5: 2026-05-07 | C5: Jože | D5: Terms | E5: Rule-of-7 details (70 words, 7 contacts, last-7 retention) belong in T&C, not on landing. | F5: S-003 | G5: todo
A6: 5 | B6: 2026-05-07 | C6: Jože | D6: Terms | E6: Suspension wording: 'Accounts that break these rules may be suspended' (and fix typo 'suspened'). | F6: S-004 | G6: todo
A7: 6 | B7: 2026-05-07 | C7: Jože | D7: Logo | E7: Like the logo — drop the 'Rule of 7' script underneath. | F7: S-005 | G7: todo
A8: 7 | B8: 2026-05-07 | C8: Jože | D8: Logo | E8: Could we add a small globe with a man in front, as on the original paper? | F8: S-006 | G8: todo
A9: 8 | B9: 2026-05-07 | C9: Jože | D9: Phone auth | E9: Add country code +386 (Slovenia) so we can test on phones. | F9: S-007 | G9: todo
A10: 9 | B10: 2026-05-07 | C10: Jože | D10: QA | E10: When technically ready, test on the phones and communication. | F10: S-008 | G10: todo
A11: 10 | B11: 2026-05-10 | C11: Jože | D11: Hero correction | E11: Keep 'Communication That Matters' as H1 (was never meant to be removed); 'Your World's chart of Communication' is the H2 below it. | F11: S-001 (corrected), S-010 | G11: todo
A12: 11 | B12: 2026-05-10 | C12: Jože | D12: Contact email | E12: Change interactiveintel@gmail.com to info@copyme1.com everywhere. | F12: S-009 | G12: todo
A13: 12 | B13: 2026-05-10 | C13: Jože | D13: Investors | E13: Search for other potential investment targets and provide a list (beyond Boscarol). | F13: B-014 | G13: todo
... A16: 15 | B16: 2026-05-10 | C16: Jože | D16: Use of funds | E16: Show use of proceeds for the €1M. | F16: B-013 | G16: todo

Sheet Feedback 3 Deltas
A1: Feedback 3 (2026-05-10) — what's new
A3: 5 new asks beyond what Feedback 2 already covered.
A5: Ask | B5: New sprint(s) | C5: Target close | D5: Status
A6: Hero — keep 'Communication That Matters'; add H2 | B6: S-001 (corrected), S-010 | C6: 2026-05-12 | D6: todo
A7: Contact email → info@copyme1.com | B7: S-009 | C7: 2026-05-12 | D7: todo
A8: Use of proceeds for €1M | B8: B-013 | C8: 2026-05-29 | D8: todo
A9: Additional investor target list (≥21) | B9: B-014 | C9: 2026-05-29 | D9: todo
A10: Timeline-to-launch communique | B10: B-015 | C10: 2026-05-13 | D10: todo
A11: Definition of 'Customer-ready' | B11: B-016 | C11: 2026-05-13 | D11: todo

Sheet Capital Plan
A1: Capital Plan — €1M angel raise (placeholder)
A3: Note: Refine in sprint B-011. All figures in EUR.
A5: Quarter | B5: Eng salaries | C5: Infra/Vercel/SMS/AI | D5: Legal/Compliance | E5: Marketing/PR | F5: Other | G5: Quarter total | H5: Cumulative spend | I5: Remaining of €1M
A6: Q3 2026 | B6: 60000 | C6: 12000 | D6: 8000 | E6: 25000 | F6: 5000 | G6: =SUM(B6:F6) -> 110000 | H6: =G6 -> 110000 | I6: =1000000-H6 -> 890000
A7: Q4 2026 | B7: 75000 | C7: 15000 | D7: 5000 | E7: 40000 | F7: 5000 | G7: =SUM(B7:F7) -> 140000 | H7: =H6+G7 -> 250000 | I7: =1000000-H7 -> 750000
A8: Q1 2027 | B8: 90000 | C8: 20000 | D8: 4000 | E8: 60000 | F8: 5000 | G8: =SUM(B8:F8) -> 179000 | H8: =H7+G8 -> 429000 | I8: =1000000-H8 -> 571000
A9: Q2 2027 | B9: 90000 | C9: 25000 | D9: 4000 | E9: 60000 | F9: 5000 | G9: =SUM(B9:F9) -> 184000 | H9: =H8+G9 -> 613000 | I9: =1000000-H9 -> 387000
A10: Q3 2027 | B10: 95000 | C10: 30000 | D10: 4000 | E10: 70000 | F10: 5000 | G10: =SUM(B10:F10) -> 204000 | H10: =H9+G10 -> 817000 | I10: =1000000-H10 -> 183000
A11: Q4 2027 | B11: 95000 | C11: 35000 | D11: 4000 | E11: 80000 | F11: 5000 | G11: =SUM(B11:F11) -> 219000 | H11: =H10+G11 -> 1036000 | I11: =1000000-H11 -> -36000
A12: TOTAL | B12: =SUM(B6:B11) -> 505000 | C12: =SUM(C6:C11) -> 137000 | D12: =SUM(D6:D11) -> 29000 | E12: =SUM(E6:E11) -> 335000 | F12: =SUM(F6:F11) -> 30000 | G12: =SUM(G6:G11) -> 1036000
